odoo/addons/website_user_login_redirect_custom/README.rst
odoo/addons/website_user_login_redirect_custom/__init__.py
odoo/addons/website_user_login_redirect_custom/__manifest__.py
odoo/addons/website_user_login_redirect_custom/controllers/__init__.py
odoo/addons/website_user_login_redirect_custom/controllers/main.py
odoo/addons/website_user_login_redirect_custom/data/ir_config_parameter_data.xml
odoo/addons/website_user_login_redirect_custom/i18n/it.po
odoo/addons/website_user_login_redirect_custom/i18n/website_user_login_redirect_custom.pot
odoo/addons/website_user_login_redirect_custom/models/__init__.py
odoo/addons/website_user_login_redirect_custom/models/res_config_settings.py
odoo/addons/website_user_login_redirect_custom/readme/CONFIGURE.md
odoo/addons/website_user_login_redirect_custom/readme/CONTEXT.md
odoo/addons/website_user_login_redirect_custom/readme/CONTRIBUTORS.md
odoo/addons/website_user_login_redirect_custom/readme/DESCRIPTION.md
odoo/addons/website_user_login_redirect_custom/readme/USAGE.md
odoo/addons/website_user_login_redirect_custom/readme/newsfragments/.gitkeep
odoo/addons/website_user_login_redirect_custom/static/description/icon.png
odoo/addons/website_user_login_redirect_custom/static/description/icon.svg
odoo/addons/website_user_login_redirect_custom/static/description/index.html
odoo/addons/website_user_login_redirect_custom/tests/__init__.py
odoo/addons/website_user_login_redirect_custom/tests/test_website_login_redirect.py
odoo/addons/website_user_login_redirect_custom/views/res_config_settings_views.xml
odoo14_addon_website_user_login_redirect_custom-14.0.1.0.1.dev3.dist-info/METADATA
odoo14_addon_website_user_login_redirect_custom-14.0.1.0.1.dev3.dist-info/WHEEL
odoo14_addon_website_user_login_redirect_custom-14.0.1.0.1.dev3.dist-info/top_level.txt
odoo14_addon_website_user_login_redirect_custom-14.0.1.0.1.dev3.dist-info/RECORD
